.gitlab-ci.yml
CHANGES.rst
LICENSE
MANIFEST.in
Manifest.in
README.md
setup.py
SoG/__init__.py
SoG/test/SoG_manuscript_generator_test.ipynb
SoG/test/SoG_manuscript_generator_test.py
SoG/test/files/.DS_Store
SoG/test/files/macro_GW_GRB.tex
SoG/tex/__init__.py
SoG/tex/generate_upload_pdf.py
SoG/tex/files/LSC_Aug2017_Virgo_Aug2017_GBM_SPIACS-aas.tex
SoG/tex/files/SoG_LIV.bib
SoG/tex/files/SoG_LIV_arxiv_aps.tex
SoG/tex/files/aas_macros.sty
SoG/tex/files/aip.bst
SoG/tex/files/notation_macros.tex
SoG/tex/files/ulem.sty
SoG_paper.egg-info/PKG-INFO
SoG_paper.egg-info/SOURCES.txt
SoG_paper.egg-info/dependency_links.txt
SoG_paper.egg-info/namespace_packages.txt
SoG_paper.egg-info/requires.txt
SoG_paper.egg-info/top_level.txt
bin/.DS_Store
bin/SoG_generate_pdf
bin/SoG_upload_pdf